tethysts/__init__.py
tethysts/main.py
tethysts/utils.py
tethysts/tests/__init__.py
tethysts/tests/test_tethysts.py
tethysts/tests/working.py
tethysts-4.5.16.dist-info/METADATA
tethysts-4.5.16.dist-info/WHEEL
tethysts-4.5.16.dist-info/licenses/LICENSE
tethysts-4.5.16.dist-info/RECORD
